tests
sdag2
